open_minded/__init__.py
open_minded/demo.py
open_minded/llm_provider_aggregator.py
open_minded/models/llm_message.py
open_minded/providers/__init__.py
open_minded/providers/base.py
open_minded/providers/deepai.py
open_minded/providers/pollinations.py
open_minded/utils/errors.py
open_minded/utils/logging.py
open_minded/utils/user_agent.py
open_minded-0.2.5.dist-info/METADATA
open_minded-0.2.5.dist-info/WHEEL
open_minded-0.2.5.dist-info/RECORD
