Metadata-Version: 2.4
Name: open-minded
Version: 0.2.5
Requires-Python: >=3.10
Requires-Dist: httpx>=0.28.1
